{"title":"Opera Mini 7.6.4 - For Slow Internet Connections [Jenu]","uid":12233331,"size":1267493,"categoryP":"applications","categoryS":"android","magnet":"?xt=urn:btih:1925727bfb96b94c018acf5ea134c92f966f7be9&amp;dn=Opera+Mini+7.6.4+-+For+Slow+Internet+Connections+%5BJenu%5D&amp;tr=udp%3A%2F%2Ftracker.openbittorrent.com%3A80&amp;tr=udp%3A%2F%2Fopen.demonii.com%3A1337&amp;tr=udp%3A%2F%2Ftracker.coppersurfer.tk%3A6969&amp;tr=udp%3A%2F%2Fexodus.desync.com%3A6969","seeders":2,"leechers":0,"uploader":"Jenu_9","files":1,"time":1439623128,"description":"Opera Mini 7.6.4\nFor Slow Internet Connections","torrent":{"xt":"urn:btih:1925727bfb96b94c018acf5ea134c92f966f7be9","amp;dn":"Opera+Mini+7.6.4+-+For+Slow+Internet+Connections+%5BJenu%5D","amp;tr":["udp%3A%2F%2Ftracker.openbittorrent.com%3A80","udp%3A%2F%2Fopen.demonii.com%3A1337","udp%3A%2F%2Ftracker.coppersurfer.tk%3A6969","udp%3A%2F%2Fexodus.desync.com%3A6969"],"infoHash":"1925727bfb96b94c018acf5ea134c92f966f7be9","infoHashBuffer":{"type":"Buffer","data":[25,37,114,123,251,150,185,76,1,138,207,94,161,52,201,47,150,111,123,233]},"announce":[],"urlList":[]}}