{"title":"Mom Has A Huge Rack 4 XXX DVDRip x264-RedSecTioN","uid":12205694,"size":2087198826,"categoryP":"porn","categoryS":"movies","magnet":"?xt=urn:btih:1ff127a4a93cfeb6291d5e0f8407a0ac19c76e8b&amp;dn=Mom+Has+A+Huge+Rack+4+XXX+DVDRip+x264-RedSecTioN&amp;tr=udp%3A%2F%2Ftracker.openbittorrent.com%3A80&amp;tr=udp%3A%2F%2Fopen.demonii.com%3A1337&amp;tr=udp%3A%2F%2Ftracker.coppersurfer.tk%3A6969&amp;tr=udp%3A%2F%2Fexodus.desync.com%3A6969","seeders":2,"leechers":1,"uploader":"xxxlavalxxx","files":6,"time":1438947664,"description":"Category\tAll Sex, MILF / Cougar, Big Tits\n\nStarring\tYuri Luv, Nina Elle, Alura Jenson, Claudia Valentine, Erica Lauren\n\nAlura Jenson - Love that black cock!Claudia Valentine - Up her tight ass!Erica Lauren - &quot;Ho&quot; for the holidays!Nina Elle - Big tit glaze!Yuri Luv - Girls love their toys!\n &lt;a href=&quot;\nhttp://imgdone.com/viewer.php?file=48676960542510848390.jpg&quot; rel=&quot;nofollow&quot; target=&quot;_NEW&quot;&gt;\nhttp://imgdone.com/viewer.php?file=48676960542510848390.jpg&lt;/a&gt;\n    \t &lt;a href=&quot;\nhttp://imgdone.com/viewer.php?file=94009922194493204922.jpg&quot; rel=&quot;nofollow&quot; target=&quot;_NEW&quot;&gt;\nhttp://imgdone.com/viewer.php?file=94009922194493204922.jpg&lt;/a&gt;\n    \t &lt;a href=&quot;\nhttp://imgdone.com/viewer.php?file=03040504530877710803.jpeg&quot; rel=&quot;nofollow&quot; target=&quot;_NEW&quot;&gt;\nhttp://imgdone.com/viewer.php?file=03040504530877710803.jpeg&lt;/a&gt;","torrent":{"xt":"urn:btih:1ff127a4a93cfeb6291d5e0f8407a0ac19c76e8b","amp;dn":"Mom+Has+A+Huge+Rack+4+XXX+DVDRip+x264-RedSecTioN","amp;tr":["udp%3A%2F%2Ftracker.openbittorrent.com%3A80","udp%3A%2F%2Fopen.demonii.com%3A1337","udp%3A%2F%2Ftracker.coppersurfer.tk%3A6969","udp%3A%2F%2Fexodus.desync.com%3A6969"],"infoHash":"1ff127a4a93cfeb6291d5e0f8407a0ac19c76e8b","infoHashBuffer":{"type":"Buffer","data":[31,241,39,164,169,60,254,182,41,29,94,15,132,7,160,172,25,199,110,139]},"announce":[],"urlList":[]}}