{"title":"Her Disciplinary Experience - Tina Hot, Brandy Smile","uid":10452594,"size":315164029,"categoryP":"porn","categoryS":"movie_clips","magnet":"?xt=urn:btih:2d834f640f5753ecde19a86a98b24a979ae4ff85&amp;dn=Her+Disciplinary+Experience+-+Tina+Hot%2C+Brandy+Smile&amp;tr=udp%3A%2F%2Ftracker.openbittorrent.com%3A80&amp;tr=udp%3A%2F%2Fopen.demonii.com%3A1337&amp;tr=udp%3A%2F%2Ftracker.coppersurfer.tk%3A6969&amp;tr=udp%3A%2F%2Fexodus.desync.com%3A6969","seeders":2,"leechers":0,"uploader":"ElitePorn","files":-1,"time":1404042860,"description":"Her Disciplinary Experience - Tina Hot, Brandy Smile\n----------------------------------------------------\n\nScreenshots:\n------------\n\n &lt;a href=&quot;\nhttp://imagescream.com/img/soft/sZ0&quot; rel=&quot;nofollow&quot; target=&quot;_NEW&quot;&gt;\nhttp://imagescream.com/img/soft/sZ0&lt;/a&gt;\n &lt;a href=&quot;\nhttp://imagescream.com/img/soft/sZ6&quot; rel=&quot;nofollow&quot; target=&quot;_NEW&quot;&gt;\nhttp://imagescream.com/img/soft/sZ6&lt;/a&gt;\n &lt;a href=&quot;\nhttp://imagescream.com/img/soft/sZJ&quot; rel=&quot;nofollow&quot; target=&quot;_NEW&quot;&gt;\nhttp://imagescream.com/img/soft/sZJ&lt;/a&gt;\n &lt;a href=&quot;\nhttp://imagescream.com/img/soft/sZW&quot; rel=&quot;nofollow&quot; target=&quot;_NEW&quot;&gt;\nhttp://imagescream.com/img/soft/sZW&lt;/a&gt;\n &lt;a href=&quot;\nhttp://imagescream.com/img/soft/sZh&quot; rel=&quot;nofollow&quot; target=&quot;_NEW&quot;&gt;\nhttp://imagescream.com/img/soft/sZh&lt;/a&gt;\n &lt;a href=&quot;\nhttp://imagescream.com/img/soft/sZ3&quot; rel=&quot;nofollow&quot; target=&quot;_NEW&quot;&gt;\nhttp://imagescream.com/img/soft/sZ3&lt;/a&gt;\n &lt;a href=&quot;\nhttp://imagescream.com/img/soft/sZD&quot; rel=&quot;nofollow&quot; target=&quot;_NEW&quot;&gt;\nhttp://imagescream.com/img/soft/sZD&lt;/a&gt;\n &lt;a href=&quot;\nhttp://imagescream.com/img/soft/sZK&quot; rel=&quot;nofollow&quot; target=&quot;_NEW&quot;&gt;\nhttp://imagescream.com/img/soft/sZK&lt;/a&gt;\n &lt;a href=&quot;\nhttp://imagescream.com/img/soft/sZP&quot; rel=&quot;nofollow&quot; target=&quot;_NEW&quot;&gt;\nhttp://imagescream.com/img/soft/sZP&lt;/a&gt;\n\n\nDuration: 29:46, Format: MP4, Resolution: 722x406, Size: 300.56 MB","torrent":{"xt":"urn:btih:2d834f640f5753ecde19a86a98b24a979ae4ff85","amp;dn":"Her+Disciplinary+Experience+-+Tina+Hot%2C+Brandy+Smile","amp;tr":["udp%3A%2F%2Ftracker.openbittorrent.com%3A80","udp%3A%2F%2Fopen.demonii.com%3A1337","udp%3A%2F%2Ftracker.coppersurfer.tk%3A6969","udp%3A%2F%2Fexodus.desync.com%3A6969"],"infoHash":"2d834f640f5753ecde19a86a98b24a979ae4ff85","infoHashBuffer":{"type":"Buffer","data":[45,131,79,100,15,87,83,236,222,25,168,106,152,178,74,151,154,228,255,133]},"announce":[],"urlList":[]}}