{"title":"FSB Litvinenko False Flag Storyville","uid":3603565,"size":273279140,"categoryP":"video","categoryS":"other","magnet":"?xt=urn:btih:46cedd9afcb3987edcd6da06360a4ffc6bac7597&amp;dn=FSB+Litvinenko+False+Flag+Storyville&amp;tr=udp%3A%2F%2Ftracker.openbittorrent.com%3A80&amp;tr=udp%3A%2F%2Fopen.demonii.com%3A1337&amp;tr=udp%3A%2F%2Ftracker.coppersurfer.tk%3A6969&amp;tr=udp%3A%2F%2Fexodus.desync.com%3A6969","seeders":2,"leechers":0,"uploader":"shuffler","files":2,"time":1169743379,"description":"Name       : Litvinenko - False Flag - Storyville\nSource     : -\nYear       : 2007\nGenre      : Docu\nCodec      : mp4\nResolution : 352x240\nSize       : 267mb\nRunTime    : 1hr\n\n  \nFor the past three years, Russian film maker Andrei Nekrasov had been making a documentary with the former KGB agent Alexander Litvinenko. The film focused on the growing authoritarianism of the Russian state and intimidation of the public. \nWhen Litvinenko was murdered with radioactive Polonium 210, the film had new focus. It was to his friend Andrei that Litvinenko said in hospital, &quot;They got me, but they won&amp;#039;t get us all&quot;. Nekrasov filmed at his friend&amp;#039;s hospital bedside \nand talked to family and friends to build this personal portrait of a man he describes as a hero...\n\nMore on the ongoing war on consciousness: http://tinyurl.com/qe5u8\n======================================================================\n\nBest Viewed with !DAMN! NFO Viewer\n\n\n||  Archived and seeded by !UtopiAted!Net!   ||    &lt;a href=&quot; http://utopiated.net&quot; rel=&quot;nofollow&quot; target=&quot;_NEW&quot;&gt; http://utopiated.net&lt;/a&gt;\n\n\n","torrent":{"xt":"urn:btih:46cedd9afcb3987edcd6da06360a4ffc6bac7597","amp;dn":"FSB+Litvinenko+False+Flag+Storyville","amp;tr":["udp%3A%2F%2Ftracker.openbittorrent.com%3A80","udp%3A%2F%2Fopen.demonii.com%3A1337","udp%3A%2F%2Ftracker.coppersurfer.tk%3A6969","udp%3A%2F%2Fexodus.desync.com%3A6969"],"infoHash":"46cedd9afcb3987edcd6da06360a4ffc6bac7597","infoHashBuffer":{"type":"Buffer","data":[70,206,221,154,252,179,152,126,220,214,218,6,54,10,79,252,107,172,117,151]},"announce":[],"urlList":[]}}