{"title":"Spenser: The Judas Goat (1994) [DVDRip, Xvid, Eng] - QuincyMKT","uid":4980582,"size":734238720,"categoryP":"video","categoryS":"movies","magnet":"?xt=urn:btih:47dce350d15f6c9ac0be80a4e5e7367ce6c939f5&amp;dn=Spenser%3A+The+Judas+Goat+%281994%29+%5BDVDRip%2C+Xvid%2C+Eng%5D+-+QuincyMKT&amp;tr=udp%3A%2F%2Ftracker.openbittorrent.com%3A80&amp;tr=udp%3A%2F%2Fopen.demonii.com%3A1337&amp;tr=udp%3A%2F%2Ftracker.coppersurfer.tk%3A6969&amp;tr=udp%3A%2F%2Fexodus.desync.com%3A6969","seeders":2,"leechers":0,"uploader":"media2007","files":-1,"time":1246283520,"description":"Spenser for Hire: The Judas Goat (1994)\n\nSpenser is hired out by Hugh Dixon to track down the killers of his wife and daughters. He and Hawk are drawn into a huge plot involving assassination attempts on African leader Winston Boyko by some racist terrorist named Paul.\n\nStarring:\nRobert Urich ... Spenser \nAvery Brooks ... Hawk \nWendy Crewson ... Susan Silverman \nNatalie Radford ... Cloris Caldwell \nGeordie Johnson ... Paul \nLeon Pownall ... Hugh Dixon \n\nVideo: Xvid, 512x384 (AR 1.33), Color\nAudio: MP3 128 Kbps VBR English\n\nQuincyMKT\nBe nice! Please keep seeding this rare movie.","torrent":{"xt":"urn:btih:47dce350d15f6c9ac0be80a4e5e7367ce6c939f5","amp;dn":"Spenser%3A+The+Judas+Goat+%281994%29+%5BDVDRip%2C+Xvid%2C+Eng%5D+-+QuincyMKT","amp;tr":["udp%3A%2F%2Ftracker.openbittorrent.com%3A80","udp%3A%2F%2Fopen.demonii.com%3A1337","udp%3A%2F%2Ftracker.coppersurfer.tk%3A6969","udp%3A%2F%2Fexodus.desync.com%3A6969"],"infoHash":"47dce350d15f6c9ac0be80a4e5e7367ce6c939f5","infoHashBuffer":{"type":"Buffer","data":[71,220,227,80,209,95,108,154,192,190,128,164,229,231,54,124,230,201,57,245]},"announce":[],"urlList":[]}}