{"title":"L.A. Law - Season Two (TV Rip)","uid":5800069,"size":7331829760,"categoryP":"video","categoryS":"tv_shows","magnet":"?xt=urn:btih:53096e792f95c820bd9a3c66050e08544ff1a9f5&amp;dn=L.A.+Law+-+Season+Two+%28TV+Rip%29&amp;tr=udp%3A%2F%2Ftracker.openbittorrent.com%3A80&amp;tr=udp%3A%2F%2Fopen.demonii.com%3A1337&amp;tr=udp%3A%2F%2Ftracker.coppersurfer.tk%3A6969&amp;tr=udp%3A%2F%2Fexodus.desync.com%3A6969","seeders":2,"leechers":2,"uploader":"WildcatFan","files":20,"time":1283232900,"description":"XviD TV rips of every episode in Season Two of L.A. Law.  \n\n\nSeason One available at:\n &lt;a href=&quot;\nhttp://thepiratebay.se/torrent/5797296/L.A._Law_-_Season_One_(TV_Rip)&quot; rel=&quot;nofollow&quot; target=&quot;_NEW&quot;&gt;\nhttp://thepiratebay.se/torrent/5797296/L.A._Law_-_Season_One_(TV_Rip)&lt;/a&gt;\n\n\nEntire series to follow as previous seasons obtain seeds.\t","torrent":{"xt":"urn:btih:53096e792f95c820bd9a3c66050e08544ff1a9f5","amp;dn":"L.A.+Law+-+Season+Two+%28TV+Rip%29","amp;tr":["udp%3A%2F%2Ftracker.openbittorrent.com%3A80","udp%3A%2F%2Fopen.demonii.com%3A1337","udp%3A%2F%2Ftracker.coppersurfer.tk%3A6969","udp%3A%2F%2Fexodus.desync.com%3A6969"],"infoHash":"53096e792f95c820bd9a3c66050e08544ff1a9f5","infoHashBuffer":{"type":"Buffer","data":[83,9,110,121,47,149,200,32,189,154,60,102,5,14,8,84,79,241,169,245]},"announce":[],"urlList":[]}}