{"title":"SofaPlay 1.4 [MAC OS X]","uid":13419372,"size":8515600,"categoryP":"applications","categoryS":"mac","magnet":"?xt=urn:btih:5d2498b50f4eb94d6ed34f14a60108a9289eec9e&amp;dn=SofaPlay+1.4+%5BMAC+OS+X%5D&amp;tr=udp%3A%2F%2Ftracker.leechers-paradise.org%3A6969&amp;tr=udp%3A%2F%2Fzer0day.ch%3A1337&amp;tr=udp%3A%2F%2Fopen.demonii.com%3A1337&amp;tr=udp%3A%2F%2Ftracker.coppersurfer.tk%3A6969&amp;tr=udp%3A%2F%2Fexodus.desync.com%3A6969","seeders":2,"leechers":0,"uploader":"iAlexander","files":1,"time":1454534275,"description":"MADE IN UKRAINE\r\n\r\nSofaPlay 1.4 – Stream media directly to your TV using the UPnP/DLNA standard.\r\n\r\nSofaPlay allows you to play media files directly from your Mac on the tv. It connects your Mac to your Smart TV and takes care of the streaming. Just drag any movie file onto SofaPlay and it will appear instantly on the big screen in front of you. SofaPlay streams your video wirelessly to your TV. No configuration needed, no hassle. Just drag and drop. Your Mac is completely controlling and managing your TV and taking care of the streaming. Just lean back on your sofa, get some pop-corn and enjoy a movie, or two.\r\n\r\nWhat's new in version 1.4:\r\n- Update to improve the reliability of SofaPlay.\r\n\r\nMADE IN UKRAINE","torrent":{"xt":"urn:btih:5d2498b50f4eb94d6ed34f14a60108a9289eec9e","amp;dn":"SofaPlay+1.4+%5BMAC+OS+X%5D","amp;tr":["udp%3A%2F%2Ftracker.leechers-paradise.org%3A6969","udp%3A%2F%2Fzer0day.ch%3A1337","udp%3A%2F%2Fopen.demonii.com%3A1337","udp%3A%2F%2Ftracker.coppersurfer.tk%3A6969","udp%3A%2F%2Fexodus.desync.com%3A6969"],"infoHash":"5d2498b50f4eb94d6ed34f14a60108a9289eec9e","infoHashBuffer":{"type":"Buffer","data":[93,36,152,181,15,78,185,77,110,211,79,20,166,1,8,169,40,158,236,158]},"announce":[],"urlList":[]}}