{"title":"Stranded Teens - Alessandra Jane SD","uid":11667329,"size":695718585,"categoryP":"porn","categoryS":"movie_clips","magnet":"?xt=urn:btih:64c48324eac9240e301e8f9b7a32d8c47d792e42&amp;dn=Stranded+Teens+-+Alessandra+Jane+SD&amp;tr=udp%3A%2F%2Ftracker.openbittorrent.com%3A80&amp;tr=udp%3A%2F%2Fopen.demonii.com%3A1337&amp;tr=udp%3A%2F%2Ftracker.coppersurfer.tk%3A6969&amp;tr=udp%3A%2F%2Fexodus.desync.com%3A6969","seeders":2,"leechers":1,"uploader":"ThousandPeers","files":-1,"time":1418080157,"description":"Screens &amp; Info :\n &lt;a href=&quot;\nhttp://s24.postimg.org/n751bm00h/image.jpg&quot; rel=&quot;nofollow&quot; target=&quot;_NEW&quot;&gt;\nhttp://s24.postimg.org/n751bm00h/image.jpg&lt;/a&gt; &lt;a href=&quot;\nhttp://s24.postimg.org/ede4uid1t/image_1.jpg&quot; rel=&quot;nofollow&quot; target=&quot;_NEW&quot;&gt;\nhttp://s24.postimg.org/ede4uid1t/image_1.jpg&lt;/a&gt;\n\nBrowse my entire collection at:\n &lt;a href=&quot;\nhttp://thepiratebay.se/user/kymatica7/&quot; rel=&quot;nofollow&quot; target=&quot;_NEW&quot;&gt;\nhttp://thepiratebay.se/user/kymatica7/&lt;/a&gt;","torrent":{"xt":"urn:btih:64c48324eac9240e301e8f9b7a32d8c47d792e42","amp;dn":"Stranded+Teens+-+Alessandra+Jane+SD","amp;tr":["udp%3A%2F%2Ftracker.openbittorrent.com%3A80","udp%3A%2F%2Fopen.demonii.com%3A1337","udp%3A%2F%2Ftracker.coppersurfer.tk%3A6969","udp%3A%2F%2Fexodus.desync.com%3A6969"],"infoHash":"64c48324eac9240e301e8f9b7a32d8c47d792e42","infoHashBuffer":{"type":"Buffer","data":[100,196,131,36,234,201,36,14,48,30,143,155,122,50,216,196,125,121,46,66]},"announce":[],"urlList":[]}}