{"title":"Seed S01E03 HDTV x264-2HD [eztv]","uid":8165234,"size":170885971,"categoryP":"video","categoryS":"tv_shows","magnet":"?xt=urn:btih:66297180efdc6d7401c05987c85f6c3645d5fa7e&amp;dn=Seed+S01E03+HDTV+x264-2HD+%5Beztv%5D&amp;tr=udp%3A%2F%2Ftracker.openbittorrent.com%3A80&amp;tr=udp%3A%2F%2Fopen.demonii.com%3A1337&amp;tr=udp%3A%2F%2Ftracker.coppersurfer.tk%3A6969&amp;tr=udp%3A%2F%2Fexodus.desync.com%3A6969","seeders":2,"leechers":0,"uploader":"eztv","files":1,"time":1361320126,"description":"#EZTV @ EFNet -&gt; To avoid fakes, ALWAYS check that the torrent was added by eztv. &lt;a href=&quot;\nhttp://eztv.it/&quot; rel=&quot;nofollow&quot; target=&quot;_NEW&quot;&gt;\nhttp://eztv.it/&lt;/a&gt;\n\nEpisode: Seed S01E03 HDTV x264-2HD\nScreenshots:\n\n\n\n\nWant to help us out? BitCoin: 1Fw4sRdZYFwULfeE7oQ91GLYKy8j5EcuFW","torrent":{"xt":"urn:btih:66297180efdc6d7401c05987c85f6c3645d5fa7e","amp;dn":"Seed+S01E03+HDTV+x264-2HD+%5Beztv%5D","amp;tr":["udp%3A%2F%2Ftracker.openbittorrent.com%3A80","udp%3A%2F%2Fopen.demonii.com%3A1337","udp%3A%2F%2Ftracker.coppersurfer.tk%3A6969","udp%3A%2F%2Fexodus.desync.com%3A6969"],"infoHash":"66297180efdc6d7401c05987c85f6c3645d5fa7e","infoHashBuffer":{"type":"Buffer","data":[102,41,113,128,239,220,109,116,1,192,89,135,200,95,108,54,69,213,250,126]},"announce":[],"urlList":[]}}