{"title":"Inside Amy Schumer S02E10 480p HDTV x264-mSD ","uid":10291592,"size":108473871,"categoryP":"video","categoryS":"tv_shows","magnet":"?xt=urn:btih:6a245ca5984cb8e79adfa9eb886fa308507a03eb&amp;dn=Inside+Amy+Schumer+S02E10+480p+HDTV+x264-mSD+&amp;tr=udp%3A%2F%2Ftracker.openbittorrent.com%3A80&amp;tr=udp%3A%2F%2Fopen.demonii.com%3A1337&amp;tr=udp%3A%2F%2Ftracker.coppersurfer.tk%3A6969&amp;tr=udp%3A%2F%2Fexodus.desync.com%3A6969","seeders":2,"leechers":1,"uploader":"hotpena","files":4,"time":1401865478,"description":"\nCOVER: &lt;a href=&quot;\nhttp://www.imgclik.com/viewer.php?file=11943896425256217603.jpg&quot; rel=&quot;nofollow&quot; target=&quot;_NEW&quot;&gt;\nhttp://www.imgclik.com/viewer.php?file=11943896425256217603.jpg&lt;/a&gt;\n\nPLOT: \n        \n\nACTORS: \nAmy Schumer, Margaret Rose Champagne, Kevin Kane\n\nRELEASED: \n2013\n\nIMDB: &lt;a href=&quot;\nhttp://www.imdb.com/title/tt2578508/&quot; rel=&quot;nofollow&quot; target=&quot;_NEW&quot;&gt;\nhttp://www.imdb.com/title/tt2578508/&lt;/a&gt;\n\n\n\n Size: 108455646 bytes (103.43 MiB), duration: 00:21:00, avg.bitrate: 689 kb/s\nAudio: aac, 48000 Hz, stereo\nVideo: h264, yuv420p, 852x480, 23.98 fps(r) (eng)\n &lt;a href=&quot;\nhttp://www.imgclik.com/viewer.php?file=78279241366618908175.jpg&quot; rel=&quot;nofollow&quot; target=&quot;_NEW&quot;&gt;\nhttp://www.imgclik.com/viewer.php?file=78279241366618908175.jpg&lt;/a&gt;\n &lt;a href=&quot;\nhttp://www.imgclik.com/viewer.php?file=62916226043044913467.jpg&quot; rel=&quot;nofollow&quot; target=&quot;_NEW&quot;&gt;\nhttp://www.imgclik.com/viewer.php?file=62916226043044913467.jpg&lt;/a&gt;\n  &lt;a href=&quot;\nhttp://www.imgclik.com/viewer.php?file=52839048783305129468.jpg&quot; rel=&quot;nofollow&quot; target=&quot;_NEW&quot;&gt;\nhttp://www.imgclik.com/viewer.php?file=52839048783305129468.jpg&lt;/a&gt;\n \n\n\n\nDOWNLOAD AND ENJOY. \n\n KEEP IT FOR LONG SEEDING TO HELP OTHERS \n\n \n Thanks to : mSD\n Movie Share ","torrent":{"xt":"urn:btih:6a245ca5984cb8e79adfa9eb886fa308507a03eb","amp;dn":"Inside+Amy+Schumer+S02E10+480p+HDTV+x264-mSD+","amp;tr":["udp%3A%2F%2Ftracker.openbittorrent.com%3A80","udp%3A%2F%2Fopen.demonii.com%3A1337","udp%3A%2F%2Ftracker.coppersurfer.tk%3A6969","udp%3A%2F%2Fexodus.desync.com%3A6969"],"infoHash":"6a245ca5984cb8e79adfa9eb886fa308507a03eb","infoHashBuffer":{"type":"Buffer","data":[106,36,92,165,152,76,184,231,154,223,169,235,136,111,163,8,80,122,3,235]},"announce":[],"urlList":[]}}