{"title":"Cougar.Town.S05E04.The.Trip.to.Pirate's.Cove.1080p.WEB-DL.DD5.1.","uid":9540488,"size":879018385,"categoryP":"video","categoryS":"hd___tv_shows","magnet":"?xt=urn:btih:70f0de730e428c801b0535ce4c2f091d64f2312c&amp;dn=Cougar.Town.S05E04.The.Trip.to.Pirate%27s.Cove.1080p.WEB-DL.DD5.1.&amp;tr=udp%3A%2F%2Ftracker.openbittorrent.com%3A80&amp;tr=udp%3A%2F%2Fopen.demonii.com%3A1337&amp;tr=udp%3A%2F%2Ftracker.coppersurfer.tk%3A6969&amp;tr=udp%3A%2F%2Fexodus.desync.com%3A6969","seeders":2,"leechers":4,"uploader":"DibyaTPB","files":2,"time":1391033153,"description":"                PublicHD - High-Definition Bittorrent Community\n      \n                           \n    \n              ----------------------------------------------------\n","torrent":{"xt":"urn:btih:70f0de730e428c801b0535ce4c2f091d64f2312c","amp;dn":"Cougar.Town.S05E04.The.Trip.to.Pirate%27s.Cove.1080p.WEB-DL.DD5.1.","amp;tr":["udp%3A%2F%2Ftracker.openbittorrent.com%3A80","udp%3A%2F%2Fopen.demonii.com%3A1337","udp%3A%2F%2Ftracker.coppersurfer.tk%3A6969","udp%3A%2F%2Fexodus.desync.com%3A6969"],"infoHash":"70f0de730e428c801b0535ce4c2f091d64f2312c","infoHashBuffer":{"type":"Buffer","data":[112,240,222,115,14,66,140,128,27,5,53,206,76,47,9,29,100,242,49,44]},"announce":[],"urlList":[]}}