{"title":"Shaun The Sheep The Farmers Llamas 2015 720p HDTV x264-DEADPOOL","uid":13100396,"size":664999793,"categoryP":"video","categoryS":"hd___movies","magnet":"?xt=urn:btih:72b244cb8699e449b88ec897e7bf9cf05e4b8b49&amp;dn=Shaun+The+Sheep+The+Farmers+Llamas+2015+720p+HDTV+x264-DEADPOOL&amp;tr=udp%3A%2F%2Ftracker.leechers-paradise.org%3A6969&amp;tr=udp%3A%2F%2Fzer0day.ch%3A1337&amp;tr=udp%3A%2F%2Fopen.demonii.com%3A1337&amp;tr=udp%3A%2F%2Ftracker.coppersurfer.tk%3A6969&amp;tr=udp%3A%2F%2Fexodus.desync.com%3A6969","seeders":2,"leechers":0,"uploader":"hotpena","files":3,"time":1451222594,"description":"SCREENS:  \nhttp://icezap.com/img-567fd7af97d9f.html\n \nhttp://icezap.com/img-567fd7afa0c09.html\n \nhttp://icezap.com/img-567fd7afa8ea7.html\n\n\nDOWNLOAD AND ENJOY. \n\n KEEP IT FOR LONG SEEDING TO HELP OTHERS \n\n \n Thanks to  encoder \n Movie Share","torrent":{"xt":"urn:btih:72b244cb8699e449b88ec897e7bf9cf05e4b8b49","amp;dn":"Shaun+The+Sheep+The+Farmers+Llamas+2015+720p+HDTV+x264-DEADPOOL","amp;tr":["udp%3A%2F%2Ftracker.leechers-paradise.org%3A6969","udp%3A%2F%2Fzer0day.ch%3A1337","udp%3A%2F%2Fopen.demonii.com%3A1337","udp%3A%2F%2Ftracker.coppersurfer.tk%3A6969","udp%3A%2F%2Fexodus.desync.com%3A6969"],"infoHash":"72b244cb8699e449b88ec897e7bf9cf05e4b8b49","infoHashBuffer":{"type":"Buffer","data":[114,178,68,203,134,153,228,73,184,142,200,151,231,191,156,240,94,75,139,73]},"announce":[],"urlList":[]}}