{"title":"[Classic Horror] The Flesh and the Fiends (1960)  ÃŸonnieÂ®.avi","uid":5689476,"size":733937664,"categoryP":"other","categoryS":"other","magnet":"?xt=urn:btih:7b3b78a64ec9af0c76f6ba35cf75e6f647c4e1c5&amp;dn=%5BClassic+Horror%5D+The+Flesh+and+the+Fiends+%281960%29++%C3%9Fonnie%C2%AE.avi&amp;tr=udp%3A%2F%2Ftracker.openbittorrent.com%3A80&amp;tr=udp%3A%2F%2Fopen.demonii.com%3A1337&amp;tr=udp%3A%2F%2Ftracker.coppersurfer.tk%3A6969&amp;tr=udp%3A%2F%2Fexodus.desync.com%3A6969","seeders":2,"leechers":1,"uploader":"bitstreeem","files":1,"time":1279012187,"description":"Video Quality = DvD Wide Screen\n\n\nCoffins Looted! Cadavers Dissected!\n\n\n\n &lt;a href=&quot;\nhttp://www.imdb.com/title/tt0052811/&quot; rel=&quot;nofollow&quot; target=&quot;_NEW&quot;&gt;\nhttp://www.imdb.com/title/tt0052811/&lt;/a&gt;\n\n\n\n &lt;a href=&quot;\thttp://thepiratebay.se/user/bitstreeem&quot; rel=&quot;nofollow&quot; target=&quot;_NEW&quot;&gt;\thttp://thepiratebay.se/user/bitstreeem&lt;/a&gt;\t\n","torrent":{"xt":"urn:btih:7b3b78a64ec9af0c76f6ba35cf75e6f647c4e1c5","amp;dn":"%5BClassic+Horror%5D+The+Flesh+and+the+Fiends+%281960%29++%C3%9Fonnie%C2%AE.avi","amp;tr":["udp%3A%2F%2Ftracker.openbittorrent.com%3A80","udp%3A%2F%2Fopen.demonii.com%3A1337","udp%3A%2F%2Ftracker.coppersurfer.tk%3A6969","udp%3A%2F%2Fexodus.desync.com%3A6969"],"infoHash":"7b3b78a64ec9af0c76f6ba35cf75e6f647c4e1c5","infoHashBuffer":{"type":"Buffer","data":[123,59,120,166,78,201,175,12,118,246,186,53,207,117,230,246,71,196,225,197]},"announce":[],"urlList":[]}}