{"title":"LSD.The.Beyond.Within.DVDRip.x265(CaNNeD)","uid":9903220,"size":674948573,"categoryP":"video","categoryS":"movies","magnet":"?xt=urn:btih:955ac573265719deb07e085866b51a204682cade&amp;dn=LSD.The.Beyond.Within.DVDRip.x265%28CaNNeD%29&amp;tr=udp%3A%2F%2Ftracker.openbittorrent.com%3A80&amp;tr=udp%3A%2F%2Fopen.demonii.com%3A1337&amp;tr=udp%3A%2F%2Ftracker.coppersurfer.tk%3A6969&amp;tr=udp%3A%2F%2Fexodus.desync.com%3A6969","seeders":2,"leechers":0,"uploader":"cannedsam","files":3,"time":1396802769,"description":"Ripped From A DVD Image, Best quality copy i've found so far of this great documentary. You may share with the credits: Ripped By CaNNeD\n\nThis Is in x265 (HEVC) format\n\nPlease seed as i'm not going to for very long, spread the love! :)\n\nGeneral\nComplete name                            LSD.The.Beyond.Within.DVDRip.x265(CaNNeD)LSD The Beyond Within Part 1.mkv\nFormat                                   : Matroska\nFormat version                           : Version 4 / Version 2\nFile size                                : 314 MiB\nDuration                                 : 40mn 14s\nOverall bit rate                         : 1 090 Kbps\nEncoded date                             : UTC 2014-04-05 23:57:49\nWriting application                      : mkvmerge v6.8.0 ('Theme for Great Cities') 64bit built on Mar  2 2014 21:34:26\nWriting library                          : libebml v1.3.0 + libmatroska v1.4.1\n\nVideo\nID                                       : 1\nFormat                                   : HEVC\nFormat/Info                              : High Efficiency Video Coding\nCodec ID                                 : V_MPEGH/ISO/HEVC\nDuration                                 : 40mn 14s\nWidth                                    : 720 pixels\nHeight                                   : 480 pixels\nDisplay aspect ratio                     : 16:9\nFrame rate mode                          : Constant\nFrame rate                               : 25.000 fps\nStandard                                 : NTSC\nDefault                                  : Yes\nForced                                   : No\n\nAudio\nID                                       : 2\nFormat                                   : AAC\nFormat/Info                              : Advanced Audio Codec\nFormat profile                           : HE-AAC / LC\nCodec ID                                 : A_AAC\nDuration                                 : 40mn 14s\nChannel(s)                               : 2 channels\nChannel positions                        : Front: L R\nSampling rate                            : 48.0 KHz / 24.0 KHz\nCompression mode                         : Lossy\nDelay relative to video                  : 31ms\nLanguage                                 : English\nDefault                                  : Yes\nForced                                   : No\n","torrent":{"xt":"urn:btih:955ac573265719deb07e085866b51a204682cade","amp;dn":"LSD.The.Beyond.Within.DVDRip.x265%28CaNNeD%29","amp;tr":["udp%3A%2F%2Ftracker.openbittorrent.com%3A80","udp%3A%2F%2Fopen.demonii.com%3A1337","udp%3A%2F%2Ftracker.coppersurfer.tk%3A6969","udp%3A%2F%2Fexodus.desync.com%3A6969"],"infoHash":"955ac573265719deb07e085866b51a204682cade","infoHashBuffer":{"type":"Buffer","data":[149,90,197,115,38,87,25,222,176,126,8,88,102,181,26,32,70,130,202,222]},"announce":[],"urlList":[]}}