{"title":"AMERICAN_GANGSTER.mp4","uid":4670848,"size":2103642041,"categoryP":"video","categoryS":"movies","magnet":"?xt=urn:btih:9593cb1a19d5bde6bd50cbb666d08d2c0fc07245&amp;dn=AMERICAN_GANGSTER.mp4&amp;tr=udp%3A%2F%2Ftracker.openbittorrent.com%3A80&amp;tr=udp%3A%2F%2Fopen.demonii.com%3A1337&amp;tr=udp%3A%2F%2Ftracker.coppersurfer.tk%3A6969&amp;tr=udp%3A%2F%2Fexodus.desync.com%3A6969","seeders":2,"leechers":0,"uploader":"fishybay","files":1,"time":1232728753,"description":"American Gangster is a 2007 crime film directed by Ridley Scott and starring Denzel Washington and Russell Crowe. Washington portrays Frank Lucas, a real-life gangster from Harlem who smuggled heroin into the United States on American service planes returning from the Vietnam War. Crowe portrays Richie Roberts, a detective attempting to bring down Lucas' drug empire.[2] Filming was done on location in New York City. American Gangster was released in the United States and Canada on November 2, 2007.","torrent":{"xt":"urn:btih:9593cb1a19d5bde6bd50cbb666d08d2c0fc07245","amp;dn":"AMERICAN_GANGSTER.mp4","amp;tr":["udp%3A%2F%2Ftracker.openbittorrent.com%3A80","udp%3A%2F%2Fopen.demonii.com%3A1337","udp%3A%2F%2Ftracker.coppersurfer.tk%3A6969","udp%3A%2F%2Fexodus.desync.com%3A6969"],"infoHash":"9593cb1a19d5bde6bd50cbb666d08d2c0fc07245","infoHashBuffer":{"type":"Buffer","data":[149,147,203,26,25,213,189,230,189,80,203,182,102,208,141,44,15,192,114,69]},"announce":[],"urlList":[]}}