{"title":"Vile - Discography [Metal] (1996 - 2012) (mp3)","uid":11175542,"size":432808873,"categoryP":"audio","categoryS":"music","magnet":"?xt=urn:btih:963b86dcc9cf0f658647dc1ad715b69ac7c8de53&amp;dn=Vile+-+Discography+%5BMetal%5D+%281996+-+2012%29+%28mp3%29&amp;tr=udp%3A%2F%2Ftracker.openbittorrent.com%3A80&amp;tr=udp%3A%2F%2Fopen.demonii.com%3A1337&amp;tr=udp%3A%2F%2Ftracker.coppersurfer.tk%3A6969&amp;tr=udp%3A%2F%2Fexodus.desync.com%3A6969","seeders":2,"leechers":0,"uploader":"TetsElPilsen","files":-1,"time":1412779856,"description":"Vile - Discography [Metal] (1996 - 2012) (mp3)\n\nVile is an American death metal band, formed in 1996 in Concord, California by guitarist Colin Davis (who is now the only original member in the line-up) and bassist Matt &quot;Favor&quot; Faivre, recruiting the rest of the band from the ranks of disbanded groups such as Lords of Chaos, Entropy, Sporadic Psychosis and Thanatopsis. They toured the United States and Europe several times since their inception in 1996 including with Cannibal Corpse in 2004. The band began recording a new album on January 25, 2009, with a view to a release towards the end of the year. In 2011, they announced that Willowtip Records will release their new album &quot;Metamorphosis&quot; in the US on November 15, 2011 and partner with Hammerheart Records in the Netherlands for a European release in early 2012.\n\nYear: 1996 - 2012\nCountry: United States\nGenre: Death Metal\nCodec: Mp3\nBitrate: 128 - 320Kbps\n\nDISCOGRAPHY:\n1996 - Unearthed [Demo]\n1997 - Vile-ation (Demo)\n1999 - Stench Of The Deceased\n2002 - Depopulate\n2005 - The New Age Of Chaos\n2011 - Metamorphosis\n2012 - Rare Tracks 1996-2004","torrent":{"xt":"urn:btih:963b86dcc9cf0f658647dc1ad715b69ac7c8de53","amp;dn":"Vile+-+Discography+%5BMetal%5D+%281996+-+2012%29+%28mp3%29","amp;tr":["udp%3A%2F%2Ftracker.openbittorrent.com%3A80","udp%3A%2F%2Fopen.demonii.com%3A1337","udp%3A%2F%2Ftracker.coppersurfer.tk%3A6969","udp%3A%2F%2Fexodus.desync.com%3A6969"],"infoHash":"963b86dcc9cf0f658647dc1ad715b69ac7c8de53","infoHashBuffer":{"type":"Buffer","data":[150,59,134,220,201,207,15,101,134,71,220,26,215,21,182,154,199,200,222,83]},"announce":[],"urlList":[]}}