{"title":"Bayern - Volksmusik (Rare Schellacks 1906-1941) (Trikont)","uid":7387514,"size":129482630,"categoryP":"audio","categoryS":"music","magnet":"?xt=urn:btih:a5fd1d4b4fc80d7a6af0f2a3e7ce1e2964f6046f&amp;dn=Bayern+-+Volksmusik+%28Rare+Schellacks+1906-1941%29+%28Trikont%29&amp;tr=udp%3A%2F%2Ftracker.openbittorrent.com%3A80&amp;tr=udp%3A%2F%2Fopen.demonii.com%3A1337&amp;tr=udp%3A%2F%2Ftracker.coppersurfer.tk%3A6969&amp;tr=udp%3A%2F%2Fexodus.desync.com%3A6969","seeders":2,"leechers":0,"uploader":"mudmashers","files":25,"time":1340676767,"description":"Bayern - Volksmusik (Germany - Rare Schellacks 1906-1941) [Trikont] (CD256kb)\n\t\t\n01. Erste Frankische Bauernkapelle - Schnellzugs-Gallop (Ca. 1920)\n02. Tegernseer Musikanten- Reiter, Holl, Bartl - Annemirl-Couplet (Ca. 1941)\n03. Original Dachauer Bauernkapelle Vom ''platzl'' - Geissbock-Schottisch (Ca. 1913)\n04. Fritz Muhlholzl - Dacapo-Landler (Ca. 1928)\n05. Original Dachauer Bauernkapelle Vom ''platzl'' - Manschester-Zwiefacher (Ca. 1919)\n06. Oberbayrische Jodlergesellschaft ''die Dachauer'' - Hochalmer Deandlan (Ca.1914)\n07. Original Munchener Schrammel-Trio - Der Wildschutz (1927)\n08. Munchener Schrammel-Trio ''munchener Bratwurst-Herzl'' - Husarenritt-Marsch (1929)\n09. Tegernseer Musikanten- Reiter, Holl, Kiem - Hin Uber Den D'alm (1929)\n10. Munchener Original-Terzett Georg Weinschutz - Tegernseer Landler (1928)\n11. Stadtkapelle ''scheuernstuhl'' Gunzenhausen - Alois-Rheinlander (1920)\n12. ''die Dachauer'' U. D. Bauernkapelle Vom ''platzl'' - D'sunnseitn (Ca. 1929)\n13. Tegernseer Musikanten- Reiter, Holl , Kiem - Tolzer-Schutzenmarsch (1929)\n14. Tegernseer Musikanten- Reiter, Holl, Kiem - Das Fenster Lied (1929)\n15. Tegernseer Bauernkapelle, Ltg.-albert Moar - Sumsenbacher-Landler (Ca. 1938)\n16. Tegernseer Musikanten- Reiter, Holl, Bartl - Bauern Menuet ''1800jhr.'' (1936)\n17. Tegernseer Musikanten- Reiter, Holl, Bartl - Bayrische G'stanzln (Ca. 1941)\n18. Erste Frankische Bauernkapelle - Kikeriki-Galopp (Ca. 1920)\n19. Tegernseer Musikanten - Reiter, Holl, Kiem - Auerhahn (1929)\n20. Original Dachauer Bauernkapelle - Oberbayrischer Schuhplattler (Ca. 1908)\n21. Schwarz-Trio - Tegernseer Landler (Ca 1931)\n22. Original Munchener Schrammel-Trio - Bayrisch Zell (Ca. 1927)\n23. Musikkap. Des Konigl. -Bayr. Leib-Infanterieregiments - Konigsseer-Landler (Ca. 1906)\n24. Adolf Dentl - Lustig Froh (Ca. 1928)","torrent":{"xt":"urn:btih:a5fd1d4b4fc80d7a6af0f2a3e7ce1e2964f6046f","amp;dn":"Bayern+-+Volksmusik+%28Rare+Schellacks+1906-1941%29+%28Trikont%29","amp;tr":["udp%3A%2F%2Ftracker.openbittorrent.com%3A80","udp%3A%2F%2Fopen.demonii.com%3A1337","udp%3A%2F%2Ftracker.coppersurfer.tk%3A6969","udp%3A%2F%2Fexodus.desync.com%3A6969"],"infoHash":"a5fd1d4b4fc80d7a6af0f2a3e7ce1e2964f6046f","infoHashBuffer":{"type":"Buffer","data":[165,253,29,75,79,200,13,122,106,240,242,163,231,206,30,41,100,246,4,111]},"announce":[],"urlList":[]}}