{"title":"Lex The Impaler 2_XXX_Split Scenes","uid":11588736,"size":2607471123,"categoryP":"porn","categoryS":"movies","magnet":"?xt=urn:btih:a814903e5b8ead6127a4b26c5478a0e8f8586809&amp;dn=Lex+The+Impaler+2_XXX_Split+Scenes&amp;tr=udp%3A%2F%2Ftracker.openbittorrent.com%3A80&amp;tr=udp%3A%2F%2Fopen.demonii.com%3A1337&amp;tr=udp%3A%2F%2Ftracker.coppersurfer.tk%3A6969&amp;tr=udp%3A%2F%2Fexodus.desync.com%3A6969","seeders":2,"leechers":1,"uploader":"m21wolf","files":12,"time":1417204041,"description":"Lex The Impaler 2_XXX_Split Scenes\n\nStarring: \n\nShyla Stylez, Lexington Steele, Monica Sweetheart, August, Alexa Rae, Ryan Conner\n\nDescription: \n\nAlexa Bows Down to the Dark Side! Ryan gets her bubble butt popped by 13 inches of steele cock all the way up her ass! Alexa bows down to worship Lex's big black cock! Shyla gets a long anal reaming and likes it straight to her mouth! Little August takes big Lex in every conceivable position! The mighty Lexington skewers a fresh assortment of white babes for Jules Jordan's latest edition of his one-man interracial series. All hail the conquering monster cock! With an extra 26 minutes of impalement on the DVD.\n\nCover:\n &lt;a href=&quot;\nhttp://www.imgalbum.com/9z&quot; rel=&quot;nofollow&quot; target=&quot;_NEW&quot;&gt;\nhttp://www.imgalbum.com/9z&lt;/a&gt;\n &lt;a href=&quot;\nhttp://www.imgalbum.com/97&quot; rel=&quot;nofollow&quot; target=&quot;_NEW&quot;&gt;\nhttp://www.imgalbum.com/97&lt;/a&gt;\n\nThumbnail Screenshot:\n &lt;a href=&quot;\nhttp://www.imgalbum.com/6r&quot; rel=&quot;nofollow&quot; target=&quot;_NEW&quot;&gt;\nhttp://www.imgalbum.com/6r&lt;/a&gt;\n &lt;a href=&quot;\nhttp://www.imgalbum.com/6B&quot; rel=&quot;nofollow&quot; target=&quot;_NEW&quot;&gt;\nhttp://www.imgalbum.com/6B&lt;/a&gt;\n &lt;a href=&quot;\nhttp://www.imgalbum.com/6I&quot; rel=&quot;nofollow&quot; target=&quot;_NEW&quot;&gt;\nhttp://www.imgalbum.com/6I&lt;/a&gt;\n &lt;a href=&quot;\nhttp://www.imgalbum.com/6q&quot; rel=&quot;nofollow&quot; target=&quot;_NEW&quot;&gt;\nhttp://www.imgalbum.com/6q&lt;/a&gt;\n &lt;a href=&quot;\nhttp://www.imgalbum.com/6t&quot; rel=&quot;nofollow&quot; target=&quot;_NEW&quot;&gt;\nhttp://www.imgalbum.com/6t&lt;/a&gt;\n &lt;a href=&quot;\nhttp://www.imgalbum.com/62&quot; rel=&quot;nofollow&quot; target=&quot;_NEW&quot;&gt;\nhttp://www.imgalbum.com/62&lt;/a&gt;\n\nDownload, Seed &amp; Enjoy :)","torrent":{"xt":"urn:btih:a814903e5b8ead6127a4b26c5478a0e8f8586809","amp;dn":"Lex+The+Impaler+2_XXX_Split+Scenes","amp;tr":["udp%3A%2F%2Ftracker.openbittorrent.com%3A80","udp%3A%2F%2Fopen.demonii.com%3A1337","udp%3A%2F%2Ftracker.coppersurfer.tk%3A6969","udp%3A%2F%2Fexodus.desync.com%3A6969"],"infoHash":"a814903e5b8ead6127a4b26c5478a0e8f8586809","infoHashBuffer":{"type":"Buffer","data":[168,20,144,62,91,142,173,97,39,164,178,108,84,120,160,232,248,88,104,9]},"announce":[],"urlList":[]}}