{"title":"TSSeduction--TS-37647 Morgan Bailey and Alexander Gustavo","uid":11805555,"size":1993999639,"categoryP":"porn","categoryS":"hd___movies","magnet":"?xt=urn:btih:a9c22f4f9c45a451d1c37d71029cd4f96b087a26&amp;dn=TSSeduction--TS-37647+Morgan+Bailey+and+Alexander+Gustavo&amp;tr=udp%3A%2F%2Ftracker.openbittorrent.com%3A80&amp;tr=udp%3A%2F%2Fopen.demonii.com%3A1337&amp;tr=udp%3A%2F%2Ftracker.coppersurfer.tk%3A6969&amp;tr=udp%3A%2F%2Fexodus.desync.com%3A6969","seeders":2,"leechers":3,"uploader":"merzedes","files":61,"time":1428567777,"description":"\nA Perfect Punishment!\n\nApr 8, 2015 - Performers: Morgan Bailey  and  Alexander Gustavo \n\n\nMed, Hi and HD MP4 + Pics.\n\n\nA blithering Alexander Gustavo awakens in a cage, trapped in seductively beautiful Morgan Bailey's dungeon. She knows why he's there....she knows his wife sent him to learn a lesson... and to be punished. Morgan orders Alexander to worship every inch of her lithe, perfect body, starting by sucking her toes and working his way up her long, long legs. She throws him around the room, bends him over her knee and spanks his ass, then pulls out her huge cock and makes him suck it. Alexander loves every moment of his humiliating punishment, even as Morgan fucks him deep and hard. She shoots a huge load all over his quivering naked body making him her perfect bitch.\n\nScreens &lt;a href=&quot;\nhttp://www.tsseduction.com/site/shoot.jsp?shootId=37647&quot; rel=&quot;nofollow&quot; target=&quot;_NEW&quot;&gt;\nhttp://www.tsseduction.com/site/shoot.jsp?shootId=37647&lt;/a&gt;\n\nUploaded by Merzedes and Shallow2\n\n17 000 Femdom/BDSM/Fetish torrentuploads completed. Man.. feels like every 1000 goes by faster and faster ;)\n\nJust keep on leaving us the nice comments below and we are happy :)\n\nAny Questions ?? Read our FAQ!!\n  \n &lt;a href=&quot;\nhttp://s16.postimg.org/rxyfmji7p/Merzedes_Shallow2_FAQ_The_Pirate_Bay.jpg&quot; rel=&quot;nofollow&quot; target=&quot;_NEW&quot;&gt;\nhttp://s16.postimg.org/rxyfmji7p/Merzedes_Shallow2_FAQ_The_Pirate_Bay.jpg&lt;/a&gt;\n\nCheers  :-)","torrent":{"xt":"urn:btih:a9c22f4f9c45a451d1c37d71029cd4f96b087a26","amp;dn":"TSSeduction--TS-37647+Morgan+Bailey+and+Alexander+Gustavo","amp;tr":["udp%3A%2F%2Ftracker.openbittorrent.com%3A80","udp%3A%2F%2Fopen.demonii.com%3A1337","udp%3A%2F%2Ftracker.coppersurfer.tk%3A6969","udp%3A%2F%2Fexodus.desync.com%3A6969"],"infoHash":"a9c22f4f9c45a451d1c37d71029cd4f96b087a26","infoHashBuffer":{"type":"Buffer","data":[169,194,47,79,156,69,164,81,209,195,125,113,2,156,212,249,107,8,122,38]},"announce":[],"urlList":[]}}