{"title":"MilfHunter - Bedeli (Stacked Fucking / Reality Kings / 10.07.201","uid":9012591,"size":442951203,"categoryP":"porn","categoryS":"movie_clips","magnet":"?xt=urn:btih:afa9bcb0ab110a30d0ed00ccad009f45ca135dba&amp;dn=MilfHunter+-+Bedeli+%28Stacked+Fucking+%2F+Reality+Kings+%2F+10.07.201&amp;tr=udp%3A%2F%2Ftracker.openbittorrent.com%3A80&amp;tr=udp%3A%2F%2Fopen.demonii.com%3A1337&amp;tr=udp%3A%2F%2Ftracker.coppersurfer.tk%3A6969&amp;tr=udp%3A%2F%2Fexodus.desync.com%3A6969","seeders":2,"leechers":3,"uploader":"codho","files":-1,"time":1381133781,"description":"Tony met a thick, sexy blond woman named Bedeli at the club, and they hit it off. He learned she was a MILF, and her husband hadn't been doing what was needed to satisfy her. Bedeli recognized Tony from his work on the internet, which excited her. Tony got her number, called his friend who had some connections, and the date was set for some fun. They went to a pool hall where Tony gave Bedeli a private lesson. She had on a tight dress that showed off her curvaceous body, and when she took her first shot, we saw she wasn't wearing underwear. Tony also took full notice and did't waste any time exploring the possibilities. When Bedeli reacted favorably to his playful advances, the action got hot quick. Bedeli laid on the pool table and rubbed the eight ball on her pussy. Tony took this as an invitation and dove in head first to lick her pussy. Bedeli showed she was better with a cock then a pool stick, as she proceeded to suck and fuck Tony into submission. Tony shot one final shot to win the game and cover Bedeli's face in cum.\n\n\nScreenshot :\n\nhttp:","torrent":{"xt":"urn:btih:afa9bcb0ab110a30d0ed00ccad009f45ca135dba","amp;dn":"MilfHunter+-+Bedeli+%28Stacked+Fucking+%2F+Reality+Kings+%2F+10.07.201","amp;tr":["udp%3A%2F%2Ftracker.openbittorrent.com%3A80","udp%3A%2F%2Fopen.demonii.com%3A1337","udp%3A%2F%2Ftracker.coppersurfer.tk%3A6969","udp%3A%2F%2Fexodus.desync.com%3A6969"],"infoHash":"afa9bcb0ab110a30d0ed00ccad009f45ca135dba","infoHashBuffer":{"type":"Buffer","data":[175,169,188,176,171,17,10,48,208,237,0,204,173,0,159,69,202,19,93,186]},"announce":[],"urlList":[]}}