{"title":"[SeptemberCarrino.com] September Carrino - Spanish Yellow","uid":6331241,"size":220052865,"categoryP":"porn","categoryS":"movies","magnet":"?xt=urn:btih:b2d4c9359136d81ab09de9fec1c1db1e62fe52da&amp;dn=%5BSeptemberCarrino.com%5D+September+Carrino+-+Spanish+Yellow+&amp;tr=udp%3A%2F%2Ftracker.openbittorrent.com%3A80&amp;tr=udp%3A%2F%2Fopen.demonii.com%3A1337&amp;tr=udp%3A%2F%2Ftracker.coppersurfer.tk%3A6969&amp;tr=udp%3A%2F%2Fexodus.desync.com%3A6969","seeders":2,"leechers":2,"uploader":"exmnova","files":1,"time":1303293479,"description":"[SeptemberCarrino.com] September Carrino - Spanish Yellow \n &lt;a href=&quot;\nhttp://0.picswan.com/show.php/5770_1.jpg.html&quot; rel=&quot;nofollow&quot; target=&quot;_NEW&quot;&gt;\nhttp://0.picswan.com/show.php/5770_1.jpg.html&lt;/a&gt;\n &lt;a href=&quot;\nhttp://0.picswan.com/show.php/5769_2.jpg.html&quot; rel=&quot;nofollow&quot; target=&quot;_NEW&quot;&gt;\nhttp://0.picswan.com/show.php/5769_2.jpg.html&lt;/a&gt;\n","torrent":{"xt":"urn:btih:b2d4c9359136d81ab09de9fec1c1db1e62fe52da","amp;dn":"%5BSeptemberCarrino.com%5D+September+Carrino+-+Spanish+Yellow+","amp;tr":["udp%3A%2F%2Ftracker.openbittorrent.com%3A80","udp%3A%2F%2Fopen.demonii.com%3A1337","udp%3A%2F%2Ftracker.coppersurfer.tk%3A6969","udp%3A%2F%2Fexodus.desync.com%3A6969"],"infoHash":"b2d4c9359136d81ab09de9fec1c1db1e62fe52da","infoHashBuffer":{"type":"Buffer","data":[178,212,201,53,145,54,216,26,176,157,233,254,193,193,219,30,98,254,82,218]},"announce":[],"urlList":[]}}