{"title":"The refreshments.Rock`n`roll x-mas","uid":4510587,"size":116813828,"categoryP":"audio","categoryS":"music","magnet":"?xt=urn:btih:f4c659ba124719a8d3032d51a18de51ad6ec004e&amp;dn=The+refreshments.Rock%60n%60roll+x-mas&amp;tr=udp%3A%2F%2Ftracker.openbittorrent.com%3A80&amp;tr=udp%3A%2F%2Fopen.demonii.com%3A1337&amp;tr=udp%3A%2F%2Ftracker.coppersurfer.tk%3A6969&amp;tr=udp%3A%2F%2Fexodus.desync.com%3A6969","seeders":2,"leechers":0,"uploader":"rock_et","files":19,"time":1226763306,"description":"The refreshments-rock`n`roll x-mas","torrent":{"xt":"urn:btih:f4c659ba124719a8d3032d51a18de51ad6ec004e","amp;dn":"The+refreshments.Rock%60n%60roll+x-mas","amp;tr":["udp%3A%2F%2Ftracker.openbittorrent.com%3A80","udp%3A%2F%2Fopen.demonii.com%3A1337","udp%3A%2F%2Ftracker.coppersurfer.tk%3A6969","udp%3A%2F%2Fexodus.desync.com%3A6969"],"infoHash":"f4c659ba124719a8d3032d51a18de51ad6ec004e","infoHashBuffer":{"type":"Buffer","data":[244,198,89,186,18,71,25,168,211,3,45,81,161,141,229,26,214,236,0,78]},"announce":[],"urlList":[]}}