{"title":"WWW Trilogy by Robert J. Sawyer (Tagged)","uid":8509284,"size":1031783808,"categoryP":"audio","categoryS":"audio_books","magnet":"?xt=urn:btih:ffa5d94dfa2d88e161ec36c160a91f0a84768f4a&amp;dn=WWW+Trilogy+by+Robert+J.+Sawyer+%28Tagged%29&amp;tr=udp%3A%2F%2Ftracker.openbittorrent.com%3A80&amp;tr=udp%3A%2F%2Fopen.demonii.com%3A1337&amp;tr=udp%3A%2F%2Ftracker.coppersurfer.tk%3A6969&amp;tr=udp%3A%2F%2Fexodus.desync.com%3A6969","seeders":2,"leechers":0,"uploader":"Glitch02","files":26,"time":1369521322,"description":"Location: Home, Northern California, USA, Earth, Solar System, Milkyway Galaxy\nMusic: A mix of running dishwasher, laptop fan, and screenreader.\nMood: Contently optimistic\n\nWelcome to this torrent!  :)\n\nThe first two audiobooks were from TPB.  The third audiobook had been purchased and then converted into mp3.  Normally I take the time to &quot;chapter&quot; the audiobooks, but I decided not to do that this time.  Everything is properly tagged however, so enjoy!  :3\n\nWith lights and sounds,\nGlitch","torrent":{"xt":"urn:btih:ffa5d94dfa2d88e161ec36c160a91f0a84768f4a","amp;dn":"WWW+Trilogy+by+Robert+J.+Sawyer+%28Tagged%29","amp;tr":["udp%3A%2F%2Ftracker.openbittorrent.com%3A80","udp%3A%2F%2Fopen.demonii.com%3A1337","udp%3A%2F%2Ftracker.coppersurfer.tk%3A6969","udp%3A%2F%2Fexodus.desync.com%3A6969"],"infoHash":"ffa5d94dfa2d88e161ec36c160a91f0a84768f4a","infoHashBuffer":{"type":"Buffer","data":[255,165,217,77,250,45,136,225,97,236,54,193,96,169,31,10,132,118,143,74]},"announce":[],"urlList":[]}}